ono/__init__.py
ono/absorption.py
ono/accessories.py
ono/acquisition.py
ono/apertur.py
ono/beam_splitter.py
ono/bruker_opus_filereader.py
ono/component.py
ono/detector.py
ono/double_sided_ftir.py
ono/embedded_webserver.py
ono/flange_board.py
ono/fourier_transform.py
ono/ifg_spectrum_data.py
ono/interferogram.py
ono/ir_source.py
ono/laser.py
ono/measurement_channel.py
ono/optical_filter.py
ono/opus_spectrum.py
ono/sample.py
ono/sample_changer.py
ono/scanner.py
ono/single_channel.py
ono/spectrometer.py
ono/spectrum.py
ono/stc16_board.py
ono/wait_for_idle.py
ono/web_client.py
ono-0.2.3.dist-info/DESCRIPTION.rst
ono-0.2.3.dist-info/METADATA
ono-0.2.3.dist-info/RECORD
ono-0.2.3.dist-info/WHEEL
ono-0.2.3.dist-info/metadata.json
ono-0.2.3.dist-info/top_level.txt
vertex_70_mock/__init__.py
vertex_70_mock/views.py
