Metadata-Version: 2.0
Name: ono
Version: 0.2.3
Summary: Bruker Opus FTIR spectroscopy clone
Home-page: https://bitbucket.org/hirschbeutel/ono
Author: hirschbeutel
Author-email: hirschbeutel@gmail.com
License: MIT
Platform: UNKNOWN
Classifier: Intended Audience :: Education
Classifier: Intended Audience :: Science/Research
Classifier: Operating System :: OS Independent
Classifier: Programming Language :: Python
Classifier: Topic :: Education
Classifier: Topic :: Scientific/Engineering
Classifier: Topic :: Scientific/Engineering :: Physics
